{
    "StormData": [
        {
            "topology.name": "PairArbitrageTopology_04",
            "storm.cluster.mode": "distributed",
            "topology.bolt.parallel": "1",
            "topology.spout.parallel": "1",
            "topology.optimize": "true"
        }
    ],
    "SpoutData": [
        {
            "ConsumerGroup": "ConsumerGroup_04",
            "RocketMQNameServerAddress": "182.92.150.57:9876",
            "TopicList": [
                "cex-io",
                "bitstamp"
            ],
            "InfluxDBURL": "http://182.92.150.57:8086",
            "InfluxDbName": "pair",
            "InfluxRpName": "aRetentionPolicy",
            "TickerData": [
                {
                    "exchangeName": "cex-io",
                    "tickerPair": [
                        "ETH/USD",
                        "BTC/USD"
                    ]
                },
                {
                    "exchangeName": "bitstamp",
                    "tickerPair": [
                        "ETH/USD",
                        "BTC/USD"
                    ]
                }
            ]
        }
    ]
}
